<PAMDataset>
  <SRS>PROJCS[&quot;Albers_Conical_Equal_Area&quot;,GEOGCS[&quot;GCS_North_American_1983&quot;,DATUM[&quot;D_North_American_1983&quot;,SPHEROID[&quot;GRS_1980&quot;,6378137.0,298.257222101]],PRIMEM[&quot;Greenwich&quot;,0.0],UNIT[&quot;Degree&quot;,0.0174532925199433]],PROJECTION[&quot;Albers&quot;],PARAMETER[&quot;false_easting&quot;,0.0],PARAMETER[&quot;false_northing&quot;,0.0],PARAMETER[&quot;central_meridian&quot;,-96.0],PARAMETER[&quot;standard_parallel_1&quot;,29.5],PARAMETER[&quot;standard_parallel_2&quot;,45.5],PARAMETER[&quot;latitude_of_origin&quot;,23.0],UNIT[&quot;Meter&quot;,1.0]]</SRS>
  <Metadata domain="ESRI">
    <MDI key="PyramidResamplingType">NEAREST</MDI>
  </Metadata>
  <PAMRasterBand band="1">
    <NoDataValue>-3.27680000000000E+004</NoDataValue>
    <ColorInterp>Palette</ColorInterp>
    <ColorTable>
      <Entry c1="255" c2="255" c3="255" c4="255"/>
      <Entry c1="0" c2="132" c3="125" c4="255"/>
      <Entry c1="0" c2="132" c3="125" c4="255"/>
      <Entry c1="0" c2="132" c3="125" c4="255"/>
      <Entry c1="30" c2="224" c3="159" c4="255"/>
      <Entry c1="43" c2="211" c3="53" c4="255"/>
      <Entry c1="43" c2="211" c3="53" c4="255"/>
      <Entry c1="43" c2="211" c3="53" c4="255"/>
      <Entry c1="179" c2="250" c3="176" c4="255"/>
      <Entry c1="41" c2="146" c3="45" c4="255"/>
      <Entry c1="41" c2="146" c3="45" c4="255"/>
      <Entry c1="41" c2="146" c3="45" c4="255"/>
      <Entry c1="41" c2="146" c3="45" c4="255"/>
      <Entry c1="41" c2="146" c3="45" c4="255"/>
      <Entry c1="41" c2="146" c3="45" c4="255"/>
      <Entry c1="41" c2="146" c3="45" c4="255"/>
      <Entry c1="41" c2="146" c3="45" c4="255"/>
      <Entry c1="41" c2="146" c3="45" c4="255"/>
      <Entry c1="41" c2="191" c3="0" c4="255"/>
      <Entry c1="41" c2="191" c3="0" c4="255"/>
      <Entry c1="41" c2="191" c3="0" c4="255"/>
      <Entry c1="41" c2="191" c3="0" c4="255"/>
      <Entry c1="41" c2="191" c3="0" c4="255"/>
      <Entry c1="41" c2="191" c3="0" c4="255"/>
      <Entry c1="41" c2="191" c3="0" c4="255"/>
      <Entry c1="41" c2="191" c3="0" c4="255"/>
      <Entry c1="41" c2="191" c3="0" c4="255"/>
      <Entry c1="41" c2="191" c3="0" c4="255"/>
      <Entry c1="41" c2="191" c3="0" c4="255"/>
      <Entry c1="41" c2="191" c3="0" c4="255"/>
      <Entry c1="100" c2="191" c3="0" c4="255"/>
      <Entry c1="100" c2="191" c3="0" c4="255"/>
      <Entry c1="100" c2="191" c3="0" c4="255"/>
      <Entry c1="168" c2="191" c3="45" c4="255"/>
      <Entry c1="168" c2="191" c3="45" c4="255"/>
      <Entry c1="168" c2="191" c3="45" c4="255"/>
      <Entry c1="168" c2="191" c3="45" c4="255"/>
      <Entry c1="168" c2="191" c3="45" c4="255"/>
      <Entry c1="168" c2="191" c3="45" c4="255"/>
      <Entry c1="31" c2="156" c3="92" c4="255"/>
      <Entry c1="31" c2="156" c3="92" c4="255"/>
      <Entry c1="31" c2="156" c3="92" c4="255"/>
      <Entry c1="31" c2="156" c3="92" c4="255"/>
      <Entry c1="31" c2="156" c3="92" c4="255"/>
      <Entry c1="31" c2="156" c3="92" c4="255"/>
      <Entry c1="31" c2="156" c3="92" c4="255"/>
      <Entry c1="0" c2="156" c3="143" c4="255"/>
      <Entry c1="0" c2="156" c3="143" c4="255"/>
      <Entry c1="31" c2="156" c3="80" c4="255"/>
      <Entry c1="31" c2="156" c3="80" c4="255"/>
      <Entry c1="0" c2="156" c3="133" c4="255"/>
      <Entry c1="0" c2="156" c3="133" c4="255"/>
      <Entry c1="0" c2="156" c3="133" c4="255"/>
      <Entry c1="0" c2="156" c3="133" c4="255"/>
      <Entry c1="99" c2="120" c3="92" c4="255"/>
      <Entry c1="99" c2="120" c3="92" c4="255"/>
      <Entry c1="99" c2="120" c3="92" c4="255"/>
      <Entry c1="99" c2="120" c3="92" c4="255"/>
      <Entry c1="99" c2="120" c3="92" c4="255"/>
      <Entry c1="135" c2="156" c3="92" c4="255"/>
      <Entry c1="38" c2="173" c3="0" c4="255"/>
      <Entry c1="38" c2="173" c3="0" c4="255"/>
      <Entry c1="38" c2="173" c3="0" c4="255"/>
      <Entry c1="38" c2="173" c3="0" c4="255"/>
      <Entry c1="38" c2="173" c3="0" c4="255"/>
      <Entry c1="38" c2="173" c3="0" c4="255"/>
      <Entry c1="38" c2="173" c3="0" c4="255"/>
      <Entry c1="38" c2="173" c3="0" c4="255"/>
      <Entry c1="38" c2="173" c3="0" c4="255"/>
      <Entry c1="38" c2="173" c3="0" c4="255"/>
      <Entry c1="38" c2="173" c3="0" c4="255"/>
      <Entry c1="38" c2="173" c3="0" c4="255"/>
      <Entry c1="38" c2="173" c3="0" c4="255"/>
      <Entry c1="38" c2="173" c3="0" c4="255"/>
      <Entry c1="38" c2="173" c3="0" c4="255"/>
      <Entry c1="38" c2="173" c3="0" c4="255"/>
      <Entry c1="38" c2="173" c3="0" c4="255"/>
      <Entry c1="38" c2="173" c3="0" c4="255"/>
      <Entry c1="38" c2="173" c3="0" c4="255"/>
      <Entry c1="38" c2="173" c3="0" c4="255"/>
      <Entry c1="38" c2="173" c3="0" c4="255"/>
      <Entry c1="38" c2="173" c3="0" c4="255"/>
      <Entry c1="38" c2="173" c3="0" c4="255"/>
      <Entry c1="38" c2="173" c3="0" c4="255"/>
      <Entry c1="38" c2="173" c3="0" c4="255"/>
      <Entry c1="38" c2="173" c3="0" c4="255"/>
      <Entry c1="38" c2="173" c3="0" c4="255"/>
      <Entry c1="38" c2="173" c3="0" c4="255"/>
      <Entry c1="38" c2="173" c3="0" c4="255"/>
      <Entry c1="110" c2="115" c3="0" c4="255"/>
      <Entry c1="110" c2="115" c3="0" c4="255"/>
      <Entry c1="110" c2="115" c3="0" c4="255"/>
      <Entry c1="110" c2="115" c3="0" c4="255"/>
      <Entry c1="54" c2="130" c3="0" c4="255"/>
      <Entry c1="54" c2="130" c3="0" c4="255"/>
      <Entry c1="54" c2="130" c3="0" c4="255"/>
      <Entry c1="54" c2="130" c3="0" c4="255"/>
      <Entry c1="54" c2="130" c3="0" c4="255"/>
      <Entry c1="54" c2="130" c3="0" c4="255"/>
      <Entry c1="54" c2="130" c3="0" c4="255"/>
      <Entry c1="54" c2="130" c3="0" c4="255"/>
      <Entry c1="54" c2="130" c3="0" c4="255"/>
      <Entry c1="54" c2="130" c3="0" c4="255"/>
      <Entry c1="38" c2="115" c3="0" c4="255"/>
      <Entry c1="38" c2="115" c3="0" c4="255"/>
      <Entry c1="38" c2="115" c3="0" c4="255"/>
      <Entry c1="38" c2="115" c3="0" c4="255"/>
      <Entry c1="38" c2="115" c3="0" c4="255"/>
      <Entry c1="38" c2="115" c3="0" c4="255"/>
      <Entry c1="38" c2="115" c3="0" c4="255"/>
      <Entry c1="38" c2="115" c3="0" c4="255"/>
      <Entry c1="38" c2="115" c3="0" c4="255"/>
      <Entry c1="38" c2="115" c3="0" c4="255"/>
      <Entry c1="38" c2="115" c3="0" c4="255"/>
      <Entry c1="38" c2="115" c3="0" c4="255"/>
      <Entry c1="99" c2="105" c3="0" c4="255"/>
      <Entry c1="99" c2="105" c3="0" c4="255"/>
      <Entry c1="99" c2="105" c3="0" c4="255"/>
      <Entry c1="99" c2="105" c3="0" c4="255"/>
      <Entry c1="99" c2="105" c3="0" c4="255"/>
      <Entry c1="38" c2="110" c3="0" c4="255"/>
      <Entry c1="38" c2="110" c3="0" c4="255"/>
      <Entry c1="38" c2="110" c3="0" c4="255"/>
      <Entry c1="38" c2="110" c3="0" c4="255"/>
      <Entry c1="38" c2="110" c3="0" c4="255"/>
      <Entry c1="38" c2="110" c3="0" c4="255"/>
      <Entry c1="38" c2="110" c3="0" c4="255"/>
      <Entry c1="38" c2="110" c3="0" c4="255"/>
      <Entry c1="38" c2="110" c3="0" c4="255"/>
      <Entry c1="38" c2="110" c3="0" c4="255"/>
      <Entry c1="38" c2="115" c3="87" c4="255"/>
      <Entry c1="38" c2="115" c3="87" c4="255"/>
      <Entry c1="38" c2="115" c3="87" c4="255"/>
      <Entry c1="38" c2="115" c3="87" c4="255"/>
      <Entry c1="38" c2="115" c3="87" c4="255"/>
      <Entry c1="38" c2="115" c3="87" c4="255"/>
      <Entry c1="0" c2="84" c3="0" c4="255"/>
      <Entry c1="0" c2="84" c3="0" c4="255"/>
      <Entry c1="0" c2="84" c3="0" c4="255"/>
      <Entry c1="0" c2="84" c3="0" c4="255"/>
      <Entry c1="0" c2="84" c3="0" c4="255"/>
      <Entry c1="0" c2="84" c3="0" c4="255"/>
      <Entry c1="0" c2="84" c3="0" c4="255"/>
      <Entry c1="0" c2="84" c3="0" c4="255"/>
      <Entry c1="0" c2="84" c3="0" c4="255"/>
      <Entry c1="0" c2="69" c3="0" c4="255"/>
      <Entry c1="0" c2="69" c3="0" c4="255"/>
      <Entry c1="0" c2="69" c3="0" c4="255"/>
      <Entry c1="0" c2="69" c3="0" c4="255"/>
      <Entry c1="0" c2="69" c3="0" c4="255"/>
      <Entry c1="0" c2="69" c3="0" c4="255"/>
      <Entry c1="0" c2="69" c3="0" c4="255"/>
      <Entry c1="0" c2="69" c3="0" c4="255"/>
      <Entry c1="0" c2="69" c3="0" c4="255"/>
      <Entry c1="0" c2="99" c3="20" c4="255"/>
      <Entry c1="0" c2="99" c3="20" c4="255"/>
      <Entry c1="0" c2="99" c3="20" c4="255"/>
      <Entry c1="0" c2="99" c3="20" c4="255"/>
      <Entry c1="0" c2="99" c3="20" c4="255"/>
      <Entry c1="0" c2="69" c3="50" c4="255"/>
      <Entry c1="0" c2="69" c3="50" c4="255"/>
      <Entry c1="0" c2="69" c3="50" c4="255"/>
      <Entry c1="0" c2="69" c3="50" c4="255"/>
      <Entry c1="0" c2="69" c3="50" c4="255"/>
      <Entry c1="0" c2="69" c3="50" c4="255"/>
      <Entry c1="0" c2="84" c3="69" c4="255"/>
      <Entry c1="0" c2="84" c3="69" c4="255"/>
      <Entry c1="0" c2="84" c3="69" c4="255"/>
      <Entry c1="0" c2="84" c3="69" c4="255"/>
      <Entry c1="0" c2="84" c3="69" c4="255"/>
      <Entry c1="0" c2="84" c3="69" c4="255"/>
      <Entry c1="0" c2="84" c3="69" c4="255"/>
      <Entry c1="0" c2="84" c3="69" c4="255"/>
      <Entry c1="0" c2="84" c3="69" c4="255"/>
      <Entry c1="0" c2="84" c3="69" c4="255"/>
      <Entry c1="79" c2="133" c3="120" c4="255"/>
      <Entry c1="79" c2="133" c3="120" c4="255"/>
      <Entry c1="79" c2="133" c3="120" c4="255"/>
      <Entry c1="79" c2="133" c3="120" c4="255"/>
      <Entry c1="79" c2="133" c3="120" c4="255"/>
      <Entry c1="79" c2="133" c3="120" c4="255"/>
      <Entry c1="79" c2="133" c3="120" c4="255"/>
      <Entry c1="102" c2="125" c3="22" c4="255"/>
      <Entry c1="102" c2="125" c3="22" c4="255"/>
      <Entry c1="102" c2="125" c3="22" c4="255"/>
      <Entry c1="102" c2="125" c3="22" c4="255"/>
      <Entry c1="89" c2="125" c3="22" c4="255"/>
      <Entry c1="89" c2="125" c3="22" c4="255"/>
      <Entry c1="89" c2="125" c3="22" c4="255"/>
      <Entry c1="89" c2="125" c3="22" c4="255"/>
      <Entry c1="0" c2="97" c3="115" c4="255"/>
      <Entry c1="0" c2="97" c3="115" c4="255"/>
      <Entry c1="0" c2="97" c3="115" c4="255"/>
      <Entry c1="0" c2="97" c3="115" c4="255"/>
      <Entry c1="0" c2="97" c3="115" c4="255"/>
      <Entry c1="0" c2="87" c3="130" c4="255"/>
      <Entry c1="0" c2="87" c3="130" c4="255"/>
      <Entry c1="0" c2="87" c3="130" c4="255"/>
      <Entry c1="0" c2="87" c3="130" c4="255"/>
      <Entry c1="0" c2="87" c3="130" c4="255"/>
      <Entry c1="0" c2="87" c3="130" c4="255"/>
      <Entry c1="0" c2="87" c3="130" c4="255"/>
      <Entry c1="0" c2="87" c3="130" c4="255"/>
      <Entry c1="0" c2="87" c3="130" c4="255"/>
      <Entry c1="102" c2="97" c3="150" c4="255"/>
      <Entry c1="102" c2="97" c3="150" c4="255"/>
      <Entry c1="102" c2="97" c3="150" c4="255"/>
      <Entry c1="102" c2="97" c3="150" c4="255"/>
      <Entry c1="102" c2="97" c3="150" c4="255"/>
      <Entry c1="102" c2="97" c3="150" c4="255"/>
      <Entry c1="102" c2="97" c3="150" c4="255"/>
      <Entry c1="102" c2="97" c3="150" c4="255"/>
      <Entry c1="102" c2="97" c3="150" c4="255"/>
      <Entry c1="52" c2="156" c3="121" c4="255"/>
      <Entry c1="52" c2="156" c3="121" c4="255"/>
      <Entry c1="52" c2="156" c3="121" c4="255"/>
      <Entry c1="52" c2="156" c3="121" c4="255"/>
      <Entry c1="52" c2="156" c3="121" c4="255"/>
      <Entry c1="52" c2="156" c3="121" c4="255"/>
      <Entry c1="52" c2="156" c3="121" c4="255"/>
      <Entry c1="52" c2="156" c3="121" c4="255"/>
      <Entry c1="52" c2="156" c3="121" c4="255"/>
      <Entry c1="52" c2="156" c3="121" c4="255"/>
      <Entry c1="52" c2="156" c3="121" c4="255"/>
      <Entry c1="52" c2="156" c3="121" c4="255"/>
      <Entry c1="52" c2="156" c3="121" c4="255"/>
      <Entry c1="52" c2="156" c3="121" c4="255"/>
      <Entry c1="52" c2="156" c3="121" c4="255"/>
      <Entry c1="52" c2="156" c3="121" c4="255"/>
      <Entry c1="52" c2="156" c3="121" c4="255"/>
      <Entry c1="52" c2="156" c3="121" c4="255"/>
      <Entry c1="52" c2="156" c3="121" c4="255"/>
      <Entry c1="52" c2="156" c3="121" c4="255"/>
      <Entry c1="52" c2="156" c3="121" c4="255"/>
      <Entry c1="52" c2="156" c3="121" c4="255"/>
      <Entry c1="52" c2="156" c3="121" c4="255"/>
      <Entry c1="52" c2="156" c3="163" c4="255"/>
      <Entry c1="52" c2="156" c3="163" c4="255"/>
      <Entry c1="52" c2="156" c3="163" c4="255"/>
      <Entry c1="52" c2="156" c3="163" c4="255"/>
      <Entry c1="52" c2="156" c3="163" c4="255"/>
      <Entry c1="0" c2="112" c3="156" c4="255"/>
      <Entry c1="0" c2="112" c3="156" c4="255"/>
      <Entry c1="0" c2="112" c3="156" c4="255"/>
      <Entry c1="0" c2="112" c3="156" c4="255"/>
      <Entry c1="0" c2="112" c3="156" c4="255"/>
      <Entry c1="0" c2="112" c3="156" c4="255"/>
      <Entry c1="0" c2="112" c3="156" c4="255"/>
      <Entry c1="0" c2="112" c3="156" c4="255"/>
      <Entry c1="0" c2="112" c3="156" c4="255"/>
      <Entry c1="0" c2="112" c3="156" c4="255"/>
      <Entry c1="0" c2="112" c3="156" c4="255"/>
      <Entry c1="0" c2="112" c3="156" c4="255"/>
      <Entry c1="52" c2="156" c3="161" c4="255"/>
      <Entry c1="0" c2="156" c3="122" c4="255"/>
      <Entry c1="0" c2="156" c3="122" c4="255"/>
      <Entry c1="0" c2="156" c3="122" c4="255"/>
      <Entry c1="0" c2="156" c3="122" c4="255"/>
      <Entry c1="0" c2="156" c3="122" c4="255"/>
      <Entry c1="0" c2="156" c3="122" c4="255"/>
      <Entry c1="0" c2="156" c3="122" c4="255"/>
      <Entry c1="0" c2="156" c3="122" c4="255"/>
      <Entry c1="0" c2="156" c3="122" c4="255"/>
      <Entry c1="0" c2="156" c3="122" c4="255"/>
      <Entry c1="0" c2="156" c3="122" c4="255"/>
      <Entry c1="7" c2="134" c3="129" c4="255"/>
      <Entry c1="7" c2="134" c3="129" c4="255"/>
      <Entry c1="7" c2="134" c3="129" c4="255"/>
      <Entry c1="7" c2="134" c3="129" c4="255"/>
      <Entry c1="7" c2="134" c3="129" c4="255"/>
      <Entry c1="7" c2="134" c3="129" c4="255"/>
      <Entry c1="7" c2="134" c3="129" c4="255"/>
      <Entry c1="7" c2="134" c3="129" c4="255"/>
      <Entry c1="7" c2="134" c3="161" c4="255"/>
      <Entry c1="7" c2="134" c3="161" c4="255"/>
      <Entry c1="7" c2="134" c3="161" c4="255"/>
      <Entry c1="7" c2="134" c3="161" c4="255"/>
      <Entry c1="51" c2="147" c3="163" c4="255"/>
      <Entry c1="51" c2="147" c3="163" c4="255"/>
      <Entry c1="51" c2="147" c3="163" c4="255"/>
      <Entry c1="51" c2="147" c3="163" c4="255"/>
      <Entry c1="51" c2="147" c3="163" c4="255"/>
      <Entry c1="51" c2="147" c3="163" c4="255"/>
      <Entry c1="51" c2="147" c3="163" c4="255"/>
      <Entry c1="51" c2="147" c3="163" c4="255"/>
      <Entry c1="77" c2="79" c3="38" c4="255"/>
      <Entry c1="77" c2="79" c3="38" c4="255"/>
      <Entry c1="77" c2="79" c3="38" c4="255"/>
      <Entry c1="0" c2="88" c3="120" c4="255"/>
      <Entry c1="0" c2="89" c3="77" c4="255"/>
      <Entry c1="246" c2="138" c3="18" c4="255"/>
      <Entry c1="246" c2="138" c3="18" c4="255"/>
      <Entry c1="246" c2="138" c3="18" c4="255"/>
      <Entry c1="201" c2="255" c3="240" c4="255"/>
      <Entry c1="201" c2="255" c3="240" c4="255"/>
      <Entry c1="201" c2="255" c3="240" c4="255"/>
      <Entry c1="242" c2="118" c3="18" c4="255"/>
      <Entry c1="242" c2="118" c3="18" c4="255"/>
      <Entry c1="242" c2="118" c3="18" c4="255"/>
      <Entry c1="242" c2="118" c3="18" c4="255"/>
      <Entry c1="242" c2="118" c3="18" c4="255"/>
      <Entry c1="242" c2="118" c3="18" c4="255"/>
      <Entry c1="242" c2="118" c3="18" c4="255"/>
      <Entry c1="200" c2="118" c3="18" c4="255"/>
      <Entry c1="237" c2="215" c3="141" c4="255"/>
      <Entry c1="237" c2="215" c3="141" c4="255"/>
      <Entry c1="245" c2="190" c3="99" c4="255"/>
      <Entry c1="245" c2="190" c3="99" c4="255"/>
      <Entry c1="245" c2="190" c3="99" c4="255"/>
      <Entry c1="245" c2="190" c3="99" c4="255"/>
      <Entry c1="245" c2="190" c3="99" c4="255"/>
      <Entry c1="245" c2="190" c3="99" c4="255"/>
      <Entry c1="245" c2="190" c3="99" c4="255"/>
      <Entry c1="245" c2="190" c3="99" c4="255"/>
      <Entry c1="245" c2="190" c3="99" c4="255"/>
      <Entry c1="245" c2="190" c3="99" c4="255"/>
      <Entry c1="246" c2="191" c3="99" c4="255"/>
      <Entry c1="246" c2="191" c3="99" c4="255"/>
      <Entry c1="246" c2="191" c3="150" c4="255"/>
      <Entry c1="246" c2="191" c3="150" c4="255"/>
      <Entry c1="246" c2="191" c3="150" c4="255"/>
      <Entry c1="246" c2="191" c3="150" c4="255"/>
      <Entry c1="246" c2="190" c3="99" c4="255"/>
      <Entry c1="246" c2="190" c3="99" c4="255"/>
      <Entry c1="194" c2="156" c3="100" c4="255"/>
      <Entry c1="194" c2="156" c3="100" c4="255"/>
      <Entry c1="194" c2="156" c3="100" c4="255"/>
      <Entry c1="194" c2="156" c3="100" c4="255"/>
      <Entry c1="194" c2="130" c3="54" c4="255"/>
      <Entry c1="194" c2="130" c3="54" c4="255"/>
      <Entry c1="225" c2="201" c3="100" c4="255"/>
      <Entry c1="225" c2="201" c3="100" c4="255"/>
      <Entry c1="201" c2="153" c3="100" c4="255"/>
      <Entry c1="201" c2="153" c3="100" c4="255"/>
      <Entry c1="201" c2="153" c3="100" c4="255"/>
      <Entry c1="201" c2="153" c3="100" c4="255"/>
      <Entry c1="201" c2="153" c3="100" c4="255"/>
      <Entry c1="201" c2="153" c3="100" c4="255"/>
      <Entry c1="201" c2="153" c3="100" c4="255"/>
      <Entry c1="201" c2="153" c3="100" c4="255"/>
      <Entry c1="201" c2="153" c3="100" c4="255"/>
      <Entry c1="246" c2="163" c3="102" c4="255"/>
      <Entry c1="240" c2="163" c3="102" c4="255"/>
      <Entry c1="240" c2="163" c3="102" c4="255"/>
      <Entry c1="240" c2="163" c3="102" c4="255"/>
      <Entry c1="246" c2="163" c3="90" c4="255"/>
      <Entry c1="246" c2="163" c3="90" c4="255"/>
      <Entry c1="246" c2="163" c3="90" c4="255"/>
      <Entry c1="246" c2="163" c3="90" c4="255"/>
      <Entry c1="246" c2="163" c3="90" c4="255"/>
      <Entry c1="246" c2="163" c3="90" c4="255"/>
      <Entry c1="246" c2="163" c3="90" c4="255"/>
      <Entry c1="246" c2="163" c3="90" c4="255"/>
      <Entry c1="246" c2="163" c3="102" c4="255"/>
      <Entry c1="246" c2="163" c3="102" c4="255"/>
      <Entry c1="246" c2="163" c3="102" c4="255"/>
      <Entry c1="238" c2="201" c3="113" c4="255"/>
      <Entry c1="238" c2="201" c3="113" c4="255"/>
      <Entry c1="238" c2="201" c3="113" c4="255"/>
      <Entry c1="238" c2="201" c3="113" c4="255"/>
      <Entry c1="209" c2="201" c3="113" c4="255"/>
      <Entry c1="209" c2="201" c3="113" c4="255"/>
      <Entry c1="246" c2="196" c3="102" c4="255"/>
      <Entry c1="246" c2="196" c3="102" c4="255"/>
      <Entry c1="207" c2="135" c3="102" c4="255"/>
      <Entry c1="207" c2="135" c3="102" c4="255"/>
      <Entry c1="246" c2="196" c3="166" c4="255"/>
      <Entry c1="246" c2="196" c3="166" c4="255"/>
      <Entry c1="246" c2="196" c3="166" c4="255"/>
      <Entry c1="255" c2="229" c3="74" c4="255"/>
      <Entry c1="201" c2="150" c3="117" c4="255"/>
      <Entry c1="201" c2="150" c3="117" c4="255"/>
      <Entry c1="201" c2="150" c3="117" c4="255"/>
      <Entry c1="201" c2="150" c3="117" c4="255"/>
      <Entry c1="201" c2="150" c3="117" c4="255"/>
      <Entry c1="201" c2="150" c3="117" c4="255"/>
      <Entry c1="201" c2="150" c3="117" c4="255"/>
      <Entry c1="201" c2="150" c3="117" c4="255"/>
      <Entry c1="201" c2="150" c3="117" c4="255"/>
      <Entry c1="201" c2="150" c3="117" c4="255"/>
      <Entry c1="165" c2="134" c3="89" c4="255"/>
      <Entry c1="165" c2="134" c3="89" c4="255"/>
      <Entry c1="165" c2="134" c3="89" c4="255"/>
      <Entry c1="165" c2="135" c3="90" c4="255"/>
      <Entry c1="165" c2="135" c3="90" c4="255"/>
      <Entry c1="165" c2="135" c3="90" c4="255"/>
      <Entry c1="165" c2="135" c3="61" c4="255"/>
      <Entry c1="165" c2="135" c3="61" c4="255"/>
      <Entry c1="165" c2="135" c3="61" c4="255"/>
      <Entry c1="165" c2="135" c3="61" c4="255"/>
      <Entry c1="165" c2="135" c3="61" c4="255"/>
      <Entry c1="165" c2="135" c3="61" c4="255"/>
      <Entry c1="165" c2="135" c3="61" c4="255"/>
      <Entry c1="165" c2="135" c3="61" c4="255"/>
      <Entry c1="165" c2="135" c3="61" c4="255"/>
      <Entry c1="112" c2="150" c3="86" c4="255"/>
      <Entry c1="112" c2="150" c3="86" c4="255"/>
      <Entry c1="112" c2="150" c3="86" c4="255"/>
      <Entry c1="112" c2="175" c3="186" c4="255"/>
      <Entry c1="112" c2="175" c3="86" c4="255"/>
      <Entry c1="112" c2="175" c3="86" c4="255"/>
      <Entry c1="112" c2="175" c3="227" c4="255"/>
      <Entry c1="112" c2="175" c3="227" c4="255"/>
      <Entry c1="112" c2="175" c3="227" c4="255"/>
      <Entry c1="112" c2="175" c3="227" c4="255"/>
      <Entry c1="112" c2="175" c3="180" c4="255"/>
      <Entry c1="112" c2="175" c3="180" c4="255"/>
      <Entry c1="112" c2="175" c3="180" c4="255"/>
      <Entry c1="112" c2="175" c3="180" c4="255"/>
      <Entry c1="112" c2="175" c3="180" c4="255"/>
      <Entry c1="112" c2="175" c3="180" c4="255"/>
      <Entry c1="112" c2="175" c3="180" c4="255"/>
      <Entry c1="112" c2="175" c3="180" c4="255"/>
      <Entry c1="112" c2="175" c3="180" c4="255"/>
      <Entry c1="112" c2="175" c3="180" c4="255"/>
      <Entry c1="112" c2="175" c3="180" c4="255"/>
      <Entry c1="111" c2="214" c3="227" c4="255"/>
      <Entry c1="111" c2="214" c3="227" c4="255"/>
      <Entry c1="111" c2="214" c3="227" c4="255"/>
      <Entry c1="111" c2="214" c3="227" c4="255"/>
      <Entry c1="111" c2="214" c3="227" c4="255"/>
      <Entry c1="111" c2="214" c3="227" c4="255"/>
      <Entry c1="140" c2="175" c3="227" c4="255"/>
      <Entry c1="140" c2="175" c3="227" c4="255"/>
      <Entry c1="140" c2="175" c3="227" c4="255"/>
      <Entry c1="140" c2="175" c3="227" c4="255"/>
      <Entry c1="140" c2="175" c3="227" c4="255"/>
      <Entry c1="140" c2="175" c3="227" c4="255"/>
      <Entry c1="100" c2="175" c3="227" c4="255"/>
      <Entry c1="0" c2="194" c3="196" c4="255"/>
      <Entry c1="0" c2="194" c3="196" c4="255"/>
      <Entry c1="0" c2="194" c3="196" c4="255"/>
      <Entry c1="0" c2="194" c3="196" c4="255"/>
      <Entry c1="0" c2="194" c3="196" c4="255"/>
      <Entry c1="0" c2="194" c3="195" c4="255"/>
      <Entry c1="0" c2="194" c3="195" c4="255"/>
      <Entry c1="0" c2="194" c3="195" c4="255"/>
      <Entry c1="0" c2="237" c3="252" c4="255"/>
      <Entry c1="0" c2="237" c3="252" c4="255"/>
      <Entry c1="0" c2="237" c3="252" c4="255"/>
      <Entry c1="0" c2="237" c3="252" c4="255"/>
      <Entry c1="0" c2="237" c3="252" c4="255"/>
      <Entry c1="112" c2="175" c3="200" c4="255"/>
      <Entry c1="112" c2="175" c3="200" c4="255"/>
      <Entry c1="112" c2="175" c3="200" c4="255"/>
      <Entry c1="125" c2="189" c3="199" c4="255"/>
      <Entry c1="163" c2="189" c3="232" c4="255"/>
      <Entry c1="163" c2="189" c3="232" c4="255"/>
      <Entry c1="163" c2="189" c3="232" c4="255"/>
      <Entry c1="163" c2="189" c3="232" c4="255"/>
      <Entry c1="163" c2="189" c3="232" c4="255"/>
      <Entry c1="163" c2="189" c3="232" c4="255"/>
      <Entry c1="163" c2="189" c3="232" c4="255"/>
      <Entry c1="163" c2="189" c3="232" c4="255"/>
      <Entry c1="163" c2="189" c3="232" c4="255"/>
      <Entry c1="163" c2="189" c3="255" c4="255"/>
      <Entry c1="163" c2="189" c3="214" c4="255"/>
      <Entry c1="163" c2="189" c3="214" c4="255"/>
      <Entry c1="163" c2="189" c3="214" c4="255"/>
      <Entry c1="163" c2="189" c3="214" c4="255"/>
      <Entry c1="210" c2="180" c3="140" c4="255"/>
      <Entry c1="210" c2="180" c3="140" c4="255"/>
      <Entry c1="210" c2="180" c3="140" c4="255"/>
      <Entry c1="210" c2="180" c3="140" c4="255"/>
      <Entry c1="210" c2="180" c3="140" c4="255"/>
      <Entry c1="210" c2="180" c3="140" c4="255"/>
      <Entry c1="210" c2="180" c3="140" c4="255"/>
      <Entry c1="210" c2="180" c3="140" c4="255"/>
      <Entry c1="210" c2="180" c3="140" c4="255"/>
      <Entry c1="210" c2="180" c3="140" c4="255"/>
      <Entry c1="219" c2="196" c3="184" c4="255"/>
      <Entry c1="219" c2="196" c3="184" c4="255"/>
      <Entry c1="219" c2="196" c3="184" c4="255"/>
      <Entry c1="219" c2="196" c3="184" c4="255"/>
      <Entry c1="219" c2="196" c3="184" c4="255"/>
      <Entry c1="210" c2="180" c3="139" c4="255"/>
      <Entry c1="210" c2="180" c3="139" c4="255"/>
      <Entry c1="179" c2="173" c3="171" c4="255"/>
      <Entry c1="209" c2="186" c3="180" c4="255"/>
      <Entry c1="209" c2="186" c3="180" c4="255"/>
      <Entry c1="209" c2="186" c3="180" c4="255"/>
      <Entry c1="209" c2="186" c3="180" c4="255"/>
      <Entry c1="209" c2="186" c3="180" c4="255"/>
      <Entry c1="209" c2="186" c3="180" c4="255"/>
      <Entry c1="176" c2="150" c3="125" c4="255"/>
      <Entry c1="176" c2="150" c3="125" c4="255"/>
      <Entry c1="199" c2="174" c3="168" c4="255"/>
      <Entry c1="207" c2="209" c3="168" c4="255"/>
      <Entry c1="207" c2="209" c3="168" c4="255"/>
      <Entry c1="207" c2="209" c3="168" c4="255"/>
      <Entry c1="207" c2="209" c3="168" c4="255"/>
      <Entry c1="207" c2="209" c3="168" c4="255"/>
      <Entry c1="156" c2="181" c3="125" c4="255"/>
      <Entry c1="156" c2="181" c3="125" c4="255"/>
      <Entry c1="156" c2="181" c3="125" c4="255"/>
      <Entry c1="156" c2="181" c3="125" c4="255"/>
      <Entry c1="222" c2="212" c3="145" c4="255"/>
      <Entry c1="222" c2="212" c3="145" c4="255"/>
      <Entry c1="222" c2="212" c3="145" c4="255"/>
      <Entry c1="222" c2="212" c3="145" c4="255"/>
      <Entry c1="237" c2="224" c3="242" c4="255"/>
      <Entry c1="235" c2="217" c3="230" c4="255"/>
      <Entry c1="235" c2="217" c3="230" c4="255"/>
      <Entry c1="235" c2="217" c3="230" c4="255"/>
      <Entry c1="235" c2="207" c3="201" c4="255"/>
      <Entry c1="235" c2="207" c3="201" c4="255"/>
      <Entry c1="235" c2="207" c3="201" c4="255"/>
      <Entry c1="235" c2="207" c3="201" c4="255"/>
      <Entry c1="194" c2="224" c3="18" c4="255"/>
      <Entry c1="64" c2="224" c3="237" c4="255"/>
      <Entry c1="64" c2="224" c3="237" c4="255"/>
      <Entry c1="0" c2="197" c3="255" c4="255"/>
      <Entry c1="0" c2="197" c3="255" c4="255"/>
      <Entry c1="0" c2="143" c3="255" c4="255"/>
      <Entry c1="214" c2="214" c3="214" c4="255"/>
      <Entry c1="214" c2="214" c3="214" c4="255"/>
      <Entry c1="214" c2="214" c3="214" c4="255"/>
      <Entry c1="194" c2="201" c3="191" c4="255"/>
      <Entry c1="194" c2="201" c3="191" c4="255"/>
      <Entry c1="194" c2="201" c3="191" c4="255"/>
      <Entry c1="194" c2="201" c3="191" c4="255"/>
      <Entry c1="194" c2="201" c3="191" c4="255"/>
      <Entry c1="194" c2="201" c3="191" c4="255"/>
      <Entry c1="194" c2="201" c3="191" c4="255"/>
      <Entry c1="194" c2="201" c3="191" c4="255"/>
      <Entry c1="194" c2="201" c3="191" c4="255"/>
      <Entry c1="194" c2="201" c3="180" c4="255"/>
      <Entry c1="194" c2="201" c3="180" c4="255"/>
      <Entry c1="194" c2="201" c3="180" c4="255"/>
      <Entry c1="200" c2="200" c3="200" c4="255"/>
      <Entry c1="150" c2="150" c3="150" c4="255"/>
      <Entry c1="150" c2="150" c3="150" c4="255"/>
      <Entry c1="150" c2="150" c3="150" c4="255"/>
      <Entry c1="150" c2="150" c3="150" c4="255"/>
      <Entry c1="150" c2="150" c3="150" c4="255"/>
      <Entry c1="229" c2="229" c3="224" c4="255"/>
      <Entry c1="194" c2="201" c3="200" c4="255"/>
      <Entry c1="194" c2="201" c3="200" c4="255"/>
      <Entry c1="84" c2="89" c3="87" c4="255"/>
      <Entry c1="84" c2="89" c3="87" c4="255"/>
      <Entry c1="84" c2="89" c3="87" c4="255"/>
      <Entry c1="84" c2="89" c3="87" c4="255"/>
      <Entry c1="111" c2="116" c3="114" c4="255"/>
      <Entry c1="111" c2="116" c3="114" c4="255"/>
      <Entry c1="111" c2="116" c3="114" c4="255"/>
      <Entry c1="111" c2="116" c3="114" c4="255"/>
      <Entry c1="111" c2="116" c3="114" c4="255"/>
      <Entry c1="111" c2="116" c3="114" c4="255"/>
      <Entry c1="111" c2="116" c3="114" c4="255"/>
      <Entry c1="236" c2="120" c3="241" c4="255"/>
      <Entry c1="237" c2="189" c3="242" c4="255"/>
      <Entry c1="237" c2="189" c3="242" c4="255"/>
      <Entry c1="140" c2="143" c3="145" c4="255"/>
      <Entry c1="140" c2="143" c3="145" c4="255"/>
      <Entry c1="140" c2="143" c3="145" c4="255"/>
      <Entry c1="254" c2="219" c3="193" c4="255"/>
      <Entry c1="254" c2="254" c3="193" c4="255"/>
      <Entry c1="254" c2="254" c3="193" c4="255"/>
      <Entry c1="161" c2="69" c3="156" c4="255"/>
      <Entry c1="161" c2="69" c3="156" c4="255"/>
      <Entry c1="161" c2="69" c3="156" c4="255"/>
      <Entry c1="161" c2="69" c3="156" c4="255"/>
      <Entry c1="161" c2="69" c3="156" c4="255"/>
      <Entry c1="161" c2="69" c3="156" c4="255"/>
      <Entry c1="161" c2="69" c3="156" c4="255"/>
      <Entry c1="135" c2="46" c3="38" c4="255"/>
      <Entry c1="135" c2="46" c3="38" c4="255"/>
      <Entry c1="135" c2="46" c3="38" c4="255"/>
      <Entry c1="135" c2="46" c3="38" c4="255"/>
      <Entry c1="135" c2="46" c3="38" c4="255"/>
      <Entry c1="135" c2="46" c3="38" c4="255"/>
      <Entry c1="135" c2="46" c3="38" c4="255"/>
      <Entry c1="135" c2="46" c3="38" c4="255"/>
      <Entry c1="135" c2="46" c3="38" c4="255"/>
      <Entry c1="135" c2="46" c3="38" c4="255"/>
      <Entry c1="135" c2="46" c3="38" c4="255"/>
      <Entry c1="135" c2="46" c3="38" c4="255"/>
      <Entry c1="0" c2="45" c3="194" c4="255"/>
      <Entry c1="0" c2="45" c3="194" c4="255"/>
      <Entry c1="0" c2="45" c3="194" c4="255"/>
      <Entry c1="224" c2="18" c3="66" c4="255"/>
      <Entry c1="201" c2="77" c3="66" c4="255"/>
      <Entry c1="201" c2="77" c3="66" c4="255"/>
      <Entry c1="201" c2="77" c3="66" c4="255"/>
      <Entry c1="201" c2="77" c3="66" c4="255"/>
    </ColorTable>
    <Metadata>
      <MDI key="RepresentationType">THEMATIC</MDI>
    </Metadata>
  </PAMRasterBand>
</PAMDataset>
